profilehound/__init__.py
profilehound/__main__.py
profilehound/__version__.py
profilehound/modules/__init__.py
profilehound/modules/smb.py
profilehound-0.1.1.dist-info/WHEEL
profilehound-0.1.1.dist-info/entry_points.txt
profilehound-0.1.1.dist-info/METADATA
profilehound-0.1.1.dist-info/RECORD
