Metadata-Version: 2.3
Name: profilehound
Version: 0.1.1
Summary: ProfileHound - BloodHound OpenGraph collector for user profiles stored on domain machines. Make informed decisions about looting secrets by identifying active user profiles on domain machines.
Author: m4lwhere
Requires-Dist: bhopengraph
Requires-Dist: dnspython
Requires-Dist: impacket
Requires-Dist: rich
Requires-Dist: sharehound>=1.0.2
Requires-Python: >=3.12
Project-URL: homepage, https://github.com/m4lwhere/profilehound
